readerwriterlock/__init__.py
readerwriterlock/py.typed
readerwriterlock/rwlock.py
readerwriterlock/rwlock_async.py
readerwriterlock-1.0.9.dist-info/AUTHORS.md
readerwriterlock-1.0.9.dist-info/LICENSE.txt
readerwriterlock-1.0.9.dist-info/METADATA
readerwriterlock-1.0.9.dist-info/WHEEL
readerwriterlock-1.0.9.dist-info/top_level.txt
readerwriterlock-1.0.9.dist-info/RECORD
