Metadata-Version: 2.1
Name: readerwriterlock
Version: 1.0.9
Summary: A python implementation of the three Reader-Writer problems.
Home-page: https://github.com/elarivie/pyReaderWriterLock
Author: Éric Larivière
Author-email: ericlariviere@hotmail.com
Maintainer: Éric Larivière
License: MIT
Download-URL: https://github.com/elarivie/pyReaderWriterLock
Project-URL: Source, https://github.com/elarivie/pyReaderWriterLock
Project-URL: Tracker, https://github.com/elarivie/pyReaderWriterLock/issues
Keywords: rwlock,read-write lock,lock,priority,reader,writer,fair,read,write,thread,synchronize
Platform: UNKNOWN
Classifier: Development Status :: 5 - Production/Stable
Classifier: Intended Audience :: Developers
Classifier: License :: OSI Approved :: MIT License
Classifier: Programming Language :: Python :: 3.7
Classifier: Programming Language :: Python :: 3.8
Classifier: Programming Language :: Python :: 3.9
Requires-Python: >=3.6
